MANIFEST.in
README.md
quicktest.py
settings_test.py
setup.py
django_facebook_applications.egg-info/PKG-INFO
django_facebook_applications.egg-info/SOURCES.txt
django_facebook_applications.egg-info/dependency_links.txt
django_facebook_applications.egg-info/not-zip-safe
django_facebook_applications.egg-info/requires.txt
django_facebook_applications.egg-info/top_level.txt
facebook_applications/__init__.py
facebook_applications/__init__.pyc
facebook_applications/models.py
facebook_applications/models.pyc
facebook_applications/migrations/0001_initial.py
facebook_applications/migrations/0001_initial.pyc
facebook_applications/migrations/__init__.py
facebook_applications/migrations/__init__.pyc